{
    "model_name": "CCN",
    "module_names": ["preprocessing.multi_norm",
                     "preprocessing.gaussian_receptive_fields",
                     "networks.correlation_classwise_network"],
    "cv": true,
    "GaussianReceptiveFields": {
        "n_fields": 25
    },
    "MultiNorm": {
        "type": "ss"
    },
    "CorrelationClasswiseNetwork": {
        "n_estimators": 1,
        "max_features": 1.0,
        "max_samples": 1.0,
        "time":1000,
        "t_ref":0.0,
        "w_init":0.0,
        "mu_plus":0.5,
        "mu_minus":0.25,
        "n_fields":25,
        "V_th": -69.6,
        "intervector_pause": 50,
        "ref_seq_interval": 5,
        "sigma_w": 0.0,
        "tau_m": 10.0,
        "tau_s": 0.3,
        "synapse_model": "stdp_gaussian_times_linear_with_separate_exp_r_dependence_synapse"
    }
}